{
  "type": "FeatureCollection",
  "mappers": [],
  "project": {
    "id": "29a80fe8-0fd7-4d6e-9340-b1050cbeda24",
    "name": "Generated Project",
    "begin_date": "2024-06-26T00:00:00Z",
    "end_date": "2025-06-26T00:00:00Z",
    "cec_climate_zone": null,
    "climate_zone": "4A",
    "default_template": "90.1-2013",
    "import_surrounding_buildings_as_shading": null,
    "surface_elevation": null,
    "tariff_filename": null,
    "timesteps_per_hour": 1,
    "weather_filename": "weather.epw"
  },
  "scenarios": [
    {
      "feature_mappings": [],
      "id": "87c611dc-c4da-48f5-a9b7-7263fed0a13a",
      "name": "Base Scenario"
    }
  ],
  "features": [
    {
      "type": "Feature",
      "properties": {
        "id": "1706598b-ad80-49c9-821d-324900268e20",
        "name": "Generated Home",
        "type": "Building",
        "building_type": "Single family",
        "floor_area": 2480,
        "number_of_stories": 2,
        "inspection_note": "The home, built in 1988, appears to be in good condition with a classic Colonial style. The aluminum/vinyl siding is typical for homes of this era and offers moderate insulation. The windows appear original and may benefit from upgrading to more energy-efficient models. The electric warm air heating system is functional, but checking the system's age and maintenance history is advisable. The presence of central air conditioning is a positive feature for climate control. Overall, the home is well-maintained with potential for energy efficiency improvements, particularly in window upgrades and additional insulation if needed.",
        "Year Built": "1988",
        "Total Square Feet Living Area": "2480",
        "Building Style": "COLONIAL",
        "Exterior Wall Material": "ALUMINUM/VINYL SIDING",
        "Heating Fuel Type": "ELECTRIC",
        "Heating System Type": "WARM AIR",
        "Heat/Air Cond": "AIR COND",
        "Bedrooms": "4",
        "Full Baths": "2",
        "Half Baths": "1",
        "Basement": "FULL",
        "Number of Stories": "2",
        "Grade": "B+ - GOOD +"
      },
      "geometry": {
        "type": "Point",
        "coordinates": [
          -75.1652,
          39.9526
        ]
      }
    }
  ]
}